aqwebengine/__init__.py
aqwebengine/impl.py
aqwebengine/qtx.py
aqwebengine/run.py
aqwebengine-0.0.1.dist-info/LICENSE
aqwebengine-0.0.1.dist-info/METADATA
aqwebengine-0.0.1.dist-info/WHEEL
aqwebengine-0.0.1.dist-info/top_level.txt
aqwebengine-0.0.1.dist-info/RECORD
