Metadata-Version: 2.1
Name: aqwebengine
Version: 0.0.1
Summary: Async helpers for QWebEngine
Home-page: https://github.com/innodatalabs/aqwebengine
Author: Mike Kroutikov
Author-email: mkroutikov@innodata.com
License: MIT
Platform: UNKNOWN
Classifier: Development Status :: 4 - Beta
Classifier: Intended Audience :: Developers
Classifier: License :: OSI Approved :: MIT License
Classifier: Programming Language :: Python :: 3.9
Classifier: Programming Language :: Python :: 3.10
Classifier: Topic :: Software Development :: Libraries :: Python Modules
Requires-Python: >= 3.9
